[
  {
    "id": "14b5c9eb4b48446fa6ae454b2201f77d",
    "user_id": "3074004d9cfa4fd4a459b8d4a005bf38",
    "filename": "A-sample-image-of-Bangladeshi-handwritten-prescription.jpg",
    "raw_text": "b\n2 Ts.\n2 Arvdott yf se = 2fade-8471\nD,. Eltrexiy(*r- Dore - bern\nhr -Fy!\np Te. low\n\nBical (Rong 2404) More\n\nee Me (aye tay\nPe. awe (lrg. dO) PET\nre\n\nwo",
    "medicines": [],
    "warnings": [],
    "overall_confidence": 0.18,
    "created_at": "2026-04-11T09:24:32.371641+00:00"
  },
  {
    "id": "2ae41356985b48e991010fa711d6e73e",
    "user_id": "3074004d9cfa4fd4a459b8d4a005bf38",
    "filename": "Sample medical prescription.jpg",
    "raw_text": "——<y\n\na Te. Amsot pv Se - 2fofe- 84\")\n\nb Te. EItroxiv (*P- 24040 - Mer\n\nrh -Ty!\n\nh ‘Te. ferred (Derg - 2\n\nph Yen\n\n( Ware by\n\nwy. Vave ry. otO+)- NO",
    "medicines": [
      {
        "medicine_name": "raloxifene",
        "strength": null,
        "dosage": null,
        "frequency": null,
        "duration": null,
        "instructions": null,
        "confidence": 0.55,
        "common_use": "Osteoporosis prevention in postmenopausal women",
        "allergy_warning": "Blood clots",
        "side_effects": "Hot flashes/leg cramps"
      }
    ],
    "warnings": [
      {
        "type": "low_confidence",
        "message": "Moderate confidence (55%) in reading 'raloxifene'. Please verify.",
        "severity": "medium",
        "related_medicine": "raloxifene"
      },
      {
        "type": "missing_info",
        "message": "Missing information for 'raloxifene': strength/dose, frequency, dosage form. Please check the original prescription.",
        "severity": "high",
        "related_medicine": "raloxifene"
      }
    ],
    "overall_confidence": 0.5,
    "created_at": "2026-04-11T09:36:45.001465+00:00"
  },
  {
    "id": "4f70b53e815240adbb42705896efc2c4",
    "user_id": "3074004d9cfa4fd4a459b8d4a005bf38",
    "filename": "Sample medical prescription.jpg",
    "raw_text": "——<y\n\na Te. Amsot pv Se - 2fofe- 84\")\n\nb Te. EItroxiv (*P- 24040 - Mer\n\nrh -Ty!\n\nh ‘Te. ferred (Derg - 2\n\nph Yen\n\n( Ware by\n\nwy. Vave ry. otO+)- NO",
    "medicines": [
      {
        "medicine_name": "raloxifene",
        "strength": null,
        "dosage": null,
        "frequency": null,
        "duration": null,
        "instructions": null,
        "confidence": 0.55,
        "common_use": "Osteoporosis prevention in postmenopausal women",
        "allergy_warning": "Blood clots",
        "side_effects": "Hot flashes/leg cramps"
      }
    ],
    "warnings": [
      {
        "type": "low_confidence",
        "message": "Moderate confidence (55%) in reading 'raloxifene'. Please verify.",
        "severity": "medium",
        "related_medicine": "raloxifene"
      },
      {
        "type": "missing_info",
        "message": "Missing information for 'raloxifene': strength/dose, frequency, dosage form. Please check the original prescription.",
        "severity": "high",
        "related_medicine": "raloxifene"
      }
    ],
    "overall_confidence": 0.5,
    "created_at": "2026-04-11T09:38:33.040639+00:00"
  },
  {
    "id": "06fedac97edf46f897ab6c9d132ecf3c",
    "user_id": "3074004d9cfa4fd4a459b8d4a005bf38",
    "filename": "Sample medical prescription.jpg",
    "raw_text": "——<y\n\na Te. Amsot pv Se - 2fofe- 84\")\n\nb Te. EItroxiv (*P- 24040 - Mer\n\nrh -Ty!\n\nh ‘Te. ferred (Derg - 2\n\nph Yen\n\n( Ware by\n\nwy. Vave ry. otO+)- NO",
    "medicines": [
      {
        "medicine_name": "raloxifene",
        "strength": null,
        "dosage": null,
        "frequency": null,
        "duration": null,
        "instructions": null,
        "confidence": 0.55,
        "common_use": "Osteoporosis prevention in postmenopausal women",
        "allergy_warning": "Blood clots",
        "side_effects": "Hot flashes/leg cramps"
      }
    ],
    "warnings": [
      {
        "type": "low_confidence",
        "message": "Moderate confidence (55%) in reading 'raloxifene'. Please verify.",
        "severity": "medium",
        "related_medicine": "raloxifene"
      },
      {
        "type": "missing_info",
        "message": "Missing information for 'raloxifene': strength/dose, frequency, dosage form. Please check the original prescription.",
        "severity": "high",
        "related_medicine": "raloxifene"
      }
    ],
    "overall_confidence": 0.5,
    "created_at": "2026-04-11T09:46:50.021801+00:00"
  },
  {
    "id": "691cf709378b44b98f1e2e770e3ae361",
    "user_id": "3074004d9cfa4fd4a459b8d4a005bf38",
    "filename": "Sample medical prescription.jpg",
    "raw_text": "——<y a Te. Amsot pv Se - Dfafo- 4\") b To. Eltexiv(*Y aaa h ‘Te. ferred (Derg - Lph- Yen ( Ware by a; Pe. Vave (leg. AHOH- NOT",
    "medicines": [
      {
        "medicine_name": "raloxifene",
        "strength": null,
        "dosage": null,
        "frequency": null,
        "duration": null,
        "instructions": null,
        "confidence": 0.55,
        "common_use": "Osteoporosis prevention in postmenopausal women",
        "allergy_warning": "Blood clots",
        "side_effects": "Hot flashes/leg cramps"
      }
    ],
    "warnings": [
      {
        "type": "low_confidence",
        "message": "Moderate confidence (55%) in reading 'raloxifene'. Please verify.",
        "severity": "medium",
        "related_medicine": "raloxifene"
      },
      {
        "type": "missing_info",
        "message": "Missing information for 'raloxifene': strength/dose, frequency, dosage form. Please check the original prescription.",
        "severity": "high",
        "related_medicine": "raloxifene"
      }
    ],
    "overall_confidence": 0.54,
    "created_at": "2026-04-11T10:05:20.945229+00:00"
  },
  {
    "id": "95de48bf05c74835a1f3e3e28f4b1e33",
    "user_id": "3074004d9cfa4fd4a459b8d4a005bf38",
    "filename": "Sample medical prescription.jpg",
    "raw_text": "——<y a Te. Amsot pv Se - Dfafo- 4\") b To. Eltexiv(*Y aaa h ‘Te. ferred (Derg - Lph- Yen ( Ware by a; Pe. Vave (leg. AHOH- NOT",
    "medicines": [
      {
        "medicine_name": "raloxifene",
        "strength": null,
        "dosage": null,
        "frequency": null,
        "duration": null,
        "instructions": null,
        "confidence": 0.55,
        "common_use": "Osteoporosis prevention in postmenopausal women",
        "allergy_warning": "Blood clots",
        "side_effects": "Hot flashes/leg cramps"
      }
    ],
    "warnings": [
      {
        "type": "low_confidence",
        "message": "Moderate confidence (55%) in reading 'raloxifene'. Please verify.",
        "severity": "medium",
        "related_medicine": "raloxifene"
      },
      {
        "type": "missing_info",
        "message": "Missing information for 'raloxifene': strength/dose, frequency, dosage form. Please check the original prescription.",
        "severity": "high",
        "related_medicine": "raloxifene"
      }
    ],
    "overall_confidence": 0.54,
    "created_at": "2026-04-11T10:06:11.929242+00:00"
  },
  {
    "id": "b59e2a00dbf6441c9f34a15a9395ba7c",
    "user_id": "3074004d9cfa4fd4a459b8d4a005bf38",
    "filename": "Sample medical prescription.jpg",
    "raw_text": "——<y a Te. Amsot pv Se - Dfafo- 4\") b To. Eltexiv(*Y aaa h ‘Te. ferred (Derg - Lph- Yen ( Ware by a; Pe. Vave (leg. AHOH- NOT",
    "medicines": [
      {
        "medicine_name": "raloxifene",
        "strength": null,
        "dosage": null,
        "frequency": null,
        "duration": null,
        "instructions": null,
        "confidence": 0.55,
        "common_use": "Osteoporosis prevention in postmenopausal women",
        "allergy_warning": "Blood clots",
        "side_effects": "Hot flashes/leg cramps"
      }
    ],
    "warnings": [
      {
        "type": "low_confidence",
        "message": "Moderate confidence (55%) in reading 'raloxifene'. Please verify.",
        "severity": "medium",
        "related_medicine": "raloxifene"
      },
      {
        "type": "missing_info",
        "message": "Missing information for 'raloxifene': strength/dose, frequency, dosage form. Please check the original prescription.",
        "severity": "high",
        "related_medicine": "raloxifene"
      }
    ],
    "overall_confidence": 0.54,
    "created_at": "2026-04-11T10:11:26.380575+00:00"
  }
]